ramachandranplot/__init__.py
ramachandranplot/data/rama500-general.data
ramachandranplot/data/rama500-gly-sym.data
ramachandranplot/data/rama500-prepro.data
ramachandranplot/data/rama500-pro.data
ramachandranplot-1.0.5.dist-info/LICENSE
ramachandranplot-1.0.5.dist-info/METADATA
ramachandranplot-1.0.5.dist-info/WHEEL
ramachandranplot-1.0.5.dist-info/entry_points.txt
ramachandranplot-1.0.5.dist-info/top_level.txt
ramachandranplot-1.0.5.dist-info/RECORD
