Metadata-Version: 2.1
Name: ramachandranplot
Version: 1.0.5
Summary: A Python package to get ramachandranplot for any pdb.
Home-page: https://github.com/sagarhm/Ramachandranplot
Author: Sagar H M
Author-email: sagarhm032000@gmail.com
License: MIT
Platform: UNKNOWN
Classifier: License :: OSI Approved :: MIT License
Classifier: Programming Language :: Python :: 3
Classifier: Programming Language :: Python :: 3.7
Requires-Dist: requests
